{
    "products": [
        {
            "id": "4ee4c357-f767-11ef-0a80-0e23000fd571",
            "code": "00699",
            "article": null,
            "category": "ЭЛЕКТРОНКИ/MOSMO GT 40000 ( 20 MG )",
            "categoryId": "3f60067a-f767-11ef-0a80-1a36000fe07d",
            "name": "ЭЛ.СИГ. MOSMO GT 40000 2% НИКОТИНА",
            "description": null,
            "imageURL": "https://tinyimage-prod.moysklad.ru/static/tinyimage/7bf0a89f-c191-11ee-0a80-00d6000033ae/tinyimage/13e7c058-e435-491a-8923-2acd04a73656/t.png",
            "imageURLMiniature": "https://miniature-prod.moysklad.ru/miniature/7bf0a89f-c191-11ee-0a80-00d6000033ae/documentminiature/37cd4cc8-9f5d-427e-87d3-5fb475fe6323",
            "imageURLOriginal": null,
            "price": 820.0,
            "vat": null,
            "currency": "руб",
            "uom": "шт",
            "quantity": 0.0,
            "stock": 0.0,
            "assortmentClass": "com.lognex.onlineorder.model.remap.OnlineOrderProduct",
            "isKit": false,
            "available": true
        },
        {
            "id": "d46f0f7b-f767-11ef-0a80-0c70000f8d0e",
            "code": "05300",
            "article": null,
            "category": "ЭЛЕКТРОНКИ/MOSMO GT 40000 ( 20 MG )",
            "categoryId": "3f60067a-f767-11ef-0a80-1a36000fe07d",
            "name": "ЭЛ.СИГ. MOSMO GT 40000 2% НИКОТИНА (Арбуз дыня)",
            "description": null,
            "imageURL": "https://tinyimage-prod.moysklad.ru/static/tinyimage/7bf0a89f-c191-11ee-0a80-00d6000033ae/tinyimage/13e7c058-e435-491a-8923-2acd04a73656/t.png",
            "imageURLMiniature": "https://miniature-prod.moysklad.ru/miniature/7bf0a89f-c191-11ee-0a80-00d6000033ae/documentminiature/37cd4cc8-9f5d-427e-87d3-5fb475fe6323",
            "imageURLOriginal": null,
            "price": 820.0,
            "vat": null,
            "currency": "руб",
            "uom": "шт",
            "quantity": 0.0,
            "stock": 0.0,
            "assortmentClass": "com.lognex.onlineorder.model.remap.OnlineOrderVariant",
            "isKit": false,
            "available": true
        },
        {
            "id": "d4728dc0-f767-11ef-0a80-0c70000f8d18",
            "code": "05301",
            "article": null,
            "category": "ЭЛЕКТРОНКИ/MOSMO GT 40000 ( 20 MG )",
            "categoryId": "3f60067a-f767-11ef-0a80-1a36000fe07d",
            "name": "ЭЛ.СИГ. MOSMO GT 40000 2% НИКОТИНА (Арбуз лёд)",
            "description": null,
            "imageURL": "https://tinyimage-prod.moysklad.ru/static/tinyimage/7bf0a89f-c191-11ee-0a80-00d6000033ae/tinyimage/13e7c058-e435-491a-8923-2acd04a73656/t.png",
            "imageURLMiniature": "https://miniature-prod.moysklad.ru/miniature/7bf0a89f-c191-11ee-0a80-00d6000033ae/documentminiature/37cd4cc8-9f5d-427e-87d3-5fb475fe6323",
            "imageURLOriginal": null,
            "price": 820.0,
            "vat": null,
            "currency": "руб",
            "uom": "шт",
            "quantity": 0.0,
            "stock": 0.0,
            "assortmentClass": "com.lognex.onlineorder.model.remap.OnlineOrderVariant",
            "isKit": false,
            "available": true
        },
        {
            "id": "d4758b26-f767-11ef-0a80-0c70000f8d22",
            "code": "05302",
            "article": null,
            "category": "ЭЛЕКТРОНКИ/MOSMO GT 40000 ( 20 MG )",
            "categoryId": "3f60067a-f767-11ef-0a80-1a36000fe07d",
            "name": "ЭЛ.СИГ. MOSMO GT 40000 2% НИКОТИНА (Арбузная жвачка)",
            "description": null,
            "imageURL": "https://tinyimage-prod.moysklad.ru/static/tinyimage/7bf0a89f-c191-11ee-0a80-00d6000033ae/tinyimage/13e7c058-e435-491a-8923-2acd04a73656/t.png",
            "imageURLMiniature": "https://miniature-prod.moysklad.ru/miniature/7bf0a89f-c191-11ee-0a80-00d6000033ae/documentminiature/37cd4cc8-9f5d-427e-87d3-5fb475fe6323",
            "imageURLOriginal": null,
            "price": 820.0,
            "vat": null,
            "currency": "руб",
            "uom": "шт",
            "quantity": 0.0,
            "stock": 0.0,
            "assortmentClass": "com.lognex.onlineorder.model.remap.OnlineOrderVariant",
            "isKit": false,
            "available": true
        },
        {
            "id": "d4789985-f767-11ef-0a80-0c70000f8d2c",
            "code": "05303",
            "article": null,
            "category": "ЭЛЕКТРОНКИ/MOSMO GT 40000 ( 20 MG )",
            "categoryId": "3f60067a-f767-11ef-0a80-1a36000fe07d",
            "name": "ЭЛ.СИГ. MOSMO GT 40000 2% НИКОТИНА (Банан киви)",
            "description": null,
            "imageURL": "https://tinyimage-prod.moysklad.ru/static/tinyimage/7bf0a89f-c191-11ee-0a80-00d6000033ae/tinyimage/13e7c058-e435-491a-8923-2acd04a73656/t.png",
            "imageURLMiniature": "https://miniature-prod.moysklad.ru/miniature/7bf0a89f-c191-11ee-0a80-00d6000033ae/documentminiature/37cd4cc8-9f5d-427e-87d3-5fb475fe6323",
            "imageURLOriginal": null,
            "price": 820.0,
            "vat": null,
            "currency": "руб",
            "uom": "шт",
            "quantity": 0.0,
            "stock": 0.0,
            "assortmentClass": "com.lognex.onlineorder.model.remap.OnlineOrderVariant",
            "isKit": false,
            "available": true
        },
        {
            "id": "d47b66b4-f767-11ef-0a80-0c70000f8d36",
            "code": "05304",
            "article": null,
            "category": "ЭЛЕКТРОНКИ/MOSMO GT 40000 ( 20 MG )",
            "categoryId": "3f60067a-f767-11ef-0a80-1a36000fe07d",
            "name": "ЭЛ.СИГ. MOSMO GT 40000 2% НИКОТИНА (Виноград лёд)",
            "description": null,
            "imageURL": "https://tinyimage-prod.moysklad.ru/static/tinyimage/7bf0a89f-c191-11ee-0a80-00d6000033ae/tinyimage/13e7c058-e435-491a-8923-2acd04a73656/t.png",
            "imageURLMiniature": "https://miniature-prod.moysklad.ru/miniature/7bf0a89f-c191-11ee-0a80-00d6000033ae/documentminiature/37cd4cc8-9f5d-427e-87d3-5fb475fe6323",
            "imageURLOriginal": null,
            "price": 820.0,
            "vat": null,
            "currency": "руб",
            "uom": "шт",
            "quantity": 0.0,
            "stock": 0.0,
            "assortmentClass": "com.lognex.onlineorder.model.remap.OnlineOrderVariant",
            "isKit": false,
            "available": true
        },
        {
            "id": "d47e4a26-f767-11ef-0a80-0c70000f8d40",
            "code": "05305",
            "article": null,
            "category": "ЭЛЕКТРОНКИ/MOSMO GT 40000 ( 20 MG )",
            "categoryId": "3f60067a-f767-11ef-0a80-1a36000fe07d",
            "name": "ЭЛ.СИГ. MOSMO GT 40000 2% НИКОТИНА (Вишня арбуз)",
            "description": null,
            "imageURL": "https://tinyimage-prod.moysklad.ru/static/tinyimage/7bf0a89f-c191-11ee-0a80-00d6000033ae/tinyimage/13e7c058-e435-491a-8923-2acd04a73656/t.png",
            "imageURLMiniature": "https://miniature-prod.moysklad.ru/miniature/7bf0a89f-c191-11ee-0a80-00d6000033ae/documentminiature/37cd4cc8-9f5d-427e-87d3-5fb475fe6323",
            "imageURLOriginal": null,
            "price": 820.0,
            "vat": null,
            "currency": "руб",
            "uom": "шт",
            "quantity": 0.0,
            "stock": 0.0,
            "assortmentClass": "com.lognex.onlineorder.model.remap.OnlineOrderVariant",
            "isKit": false,
            "available": true
        },
        {
            "id": "d4814508-f767-11ef-0a80-0c70000f8d4a",
            "code": "05306",
            "article": null,
            "category": "ЭЛЕКТРОНКИ/MOSMO GT 40000 ( 20 MG )",
            "categoryId": "3f60067a-f767-11ef-0a80-1a36000fe07d",
            "name": "ЭЛ.СИГ. MOSMO GT 40000 2% НИКОТИНА (Вишня кола)",
            "description": null,
            "imageURL": "https://tinyimage-prod.moysklad.ru/static/tinyimage/7bf0a89f-c191-11ee-0a80-00d6000033ae/tinyimage/13e7c058-e435-491a-8923-2acd04a73656/t.png",
            "imageURLMiniature": "https://miniature-prod.moysklad.ru/miniature/7bf0a89f-c191-11ee-0a80-00d6000033ae/documentminiature/37cd4cc8-9f5d-427e-87d3-5fb475fe6323",
            "imageURLOriginal": null,
            "price": 820.0,
            "vat": null,
            "currency": "руб",
            "uom": "шт",
            "quantity": 0.0,
            "stock": 0.0,
            "assortmentClass": "com.lognex.onlineorder.model.remap.OnlineOrderVariant",
            "isKit": false,
            "available": true
        },
        {
            "id": "d48427b0-f767-11ef-0a80-0c70000f8d54",
            "code": "05307",
            "article": null,
            "category": "ЭЛЕКТРОНКИ/MOSMO GT 40000 ( 20 MG )",
            "categoryId": "3f60067a-f767-11ef-0a80-1a36000fe07d",
            "name": "ЭЛ.СИГ. MOSMO GT 40000 2% НИКОТИНА (Вишня лайм)",
            "description": null,
            "imageURL": "https://tinyimage-prod.moysklad.ru/static/tinyimage/7bf0a89f-c191-11ee-0a80-00d6000033ae/tinyimage/13e7c058-e435-491a-8923-2acd04a73656/t.png",
            "imageURLMiniature": "https://miniature-prod.moysklad.ru/miniature/7bf0a89f-c191-11ee-0a80-00d6000033ae/documentminiature/37cd4cc8-9f5d-427e-87d3-5fb475fe6323",
            "imageURLOriginal": null,
            "price": 820.0,
            "vat": null,
            "currency": "руб",
            "uom": "шт",
            "quantity": 0.0,
            "stock": 0.0,
            "assortmentClass": "com.lognex.onlineorder.model.remap.OnlineOrderVariant",
            "isKit": false,
            "available": true
        },
        {
            "id": "d486fe5a-f767-11ef-0a80-0c70000f8d5e",
            "code": "05308",
            "article": null,
            "category": "ЭЛЕКТРОНКИ/MOSMO GT 40000 ( 20 MG )",
            "categoryId": "3f60067a-f767-11ef-0a80-1a36000fe07d",
            "name": "ЭЛ.СИГ. MOSMO GT 40000 2% НИКОТИНА (Гранат смородина)",
            "description": null,
            "imageURL": "https://tinyimage-prod.moysklad.ru/static/tinyimage/7bf0a89f-c191-11ee-0a80-00d6000033ae/tinyimage/13e7c058-e435-491a-8923-2acd04a73656/t.png",
            "imageURLMiniature": "https://miniature-prod.moysklad.ru/miniature/7bf0a89f-c191-11ee-0a80-00d6000033ae/documentminiature/37cd4cc8-9f5d-427e-87d3-5fb475fe6323",
            "imageURLOriginal": null,
            "price": 820.0,
            "vat": null,
            "currency": "руб",
            "uom": "шт",
            "quantity": 0.0,
            "stock": 0.0,
            "assortmentClass": "com.lognex.onlineorder.model.remap.OnlineOrderVariant",
            "isKit": false,
            "available": true
        },
        {
            "id": "d48a0554-f767-11ef-0a80-0c70000f8d68",
            "code": "05309",
            "article": null,
            "category": "ЭЛЕКТРОНКИ/MOSMO GT 40000 ( 20 MG )",
            "categoryId": "3f60067a-f767-11ef-0a80-1a36000fe07d",
            "name": "ЭЛ.СИГ. MOSMO GT 40000 2% НИКОТИНА (Клубника апельсин)",
            "description": null,
            "imageURL": "https://tinyimage-prod.moysklad.ru/static/tinyimage/7bf0a89f-c191-11ee-0a80-00d6000033ae/tinyimage/13e7c058-e435-491a-8923-2acd04a73656/t.png",
            "imageURLMiniature": "https://miniature-prod.moysklad.ru/miniature/7bf0a89f-c191-11ee-0a80-00d6000033ae/documentminiature/37cd4cc8-9f5d-427e-87d3-5fb475fe6323",
            "imageURLOriginal": null,
            "price": 820.0,
            "vat": null,
            "currency": "руб",
            "uom": "шт",
            "quantity": 0.0,
            "stock": 0.0,
            "assortmentClass": "com.lognex.onlineorder.model.remap.OnlineOrderVariant",
            "isKit": false,
            "available": true
        },
        {
            "id": "d48d0197-f767-11ef-0a80-0c70000f8d72",
            "code": "05310",
            "article": null,
            "category": "ЭЛЕКТРОНКИ/MOSMO GT 40000 ( 20 MG )",
            "categoryId": "3f60067a-f767-11ef-0a80-1a36000fe07d",
            "name": "ЭЛ.СИГ. MOSMO GT 40000 2% НИКОТИНА (Клубника киви маракуйя)",
            "description": null,
            "imageURL": "https://tinyimage-prod.moysklad.ru/static/tinyimage/7bf0a89f-c191-11ee-0a80-00d6000033ae/tinyimage/13e7c058-e435-491a-8923-2acd04a73656/t.png",
            "imageURLMiniature": "https://miniature-prod.moysklad.ru/miniature/7bf0a89f-c191-11ee-0a80-00d6000033ae/documentminiature/37cd4cc8-9f5d-427e-87d3-5fb475fe6323",
            "imageURLOriginal": null,
            "price": 820.0,
            "vat": null,
            "currency": "руб",
            "uom": "шт",
            "quantity": 0.0,
            "stock": 0.0,
            "assortmentClass": "com.lognex.onlineorder.model.remap.OnlineOrderVariant",
            "isKit": false,
            "available": true
        },
        {
            "id": "d49008cb-f767-11ef-0a80-0c70000f8d7c",
            "code": "05311",
            "article": null,
            "category": "ЭЛЕКТРОНКИ/MOSMO GT 40000 ( 20 MG )",
            "categoryId": "3f60067a-f767-11ef-0a80-1a36000fe07d",
            "name": "ЭЛ.СИГ. MOSMO GT 40000 2% НИКОТИНА (Клубника маракуйя гуава)",
            "description": null,
            "imageURL": "https://tinyimage-prod.moysklad.ru/static/tinyimage/7bf0a89f-c191-11ee-0a80-00d6000033ae/tinyimage/13e7c058-e435-491a-8923-2acd04a73656/t.png",
            "imageURLMiniature": "https://miniature-prod.moysklad.ru/miniature/7bf0a89f-c191-11ee-0a80-00d6000033ae/documentminiature/37cd4cc8-9f5d-427e-87d3-5fb475fe6323",
            "imageURLOriginal": null,
            "price": 820.0,
            "vat": null,
            "currency": "руб",
            "uom": "шт",
            "quantity": 0.0,
            "stock": 0.0,
            "assortmentClass": "com.lognex.onlineorder.model.remap.OnlineOrderVariant",
            "isKit": false,
            "available": true
        },
        {
            "id": "d4934422-f767-11ef-0a80-0c70000f8d86",
            "code": "05312",
            "article": null,
            "category": "ЭЛЕКТРОНКИ/MOSMO GT 40000 ( 20 MG )",
            "categoryId": "3f60067a-f767-11ef-0a80-1a36000fe07d",
            "name": "ЭЛ.СИГ. MOSMO GT 40000 2% НИКОТИНА (Клубника мароженое)",
            "description": null,
            "imageURL": "https://tinyimage-prod.moysklad.ru/static/tinyimage/7bf0a89f-c191-11ee-0a80-00d6000033ae/tinyimage/13e7c058-e435-491a-8923-2acd04a73656/t.png",
            "imageURLMiniature": "https://miniature-prod.moysklad.ru/miniature/7bf0a89f-c191-11ee-0a80-00d6000033ae/documentminiature/37cd4cc8-9f5d-427e-87d3-5fb475fe6323",
            "imageURLOriginal": null,
            "price": 820.0,
            "vat": null,
            "currency": "руб",
            "uom": "шт",
            "quantity": 0.0,
            "stock": 0.0,
            "assortmentClass": "com.lognex.onlineorder.model.remap.OnlineOrderVariant",
            "isKit": false,
            "available": true
        },
        {
            "id": "d496341e-f767-11ef-0a80-0c70000f8d90",
            "code": "05313",
            "article": null,
            "category": "ЭЛЕКТРОНКИ/MOSMO GT 40000 ( 20 MG )",
            "categoryId": "3f60067a-f767-11ef-0a80-1a36000fe07d",
            "name": "ЭЛ.СИГ. MOSMO GT 40000 2% НИКОТИНА (Клюква виноград яблоко)",
            "description": null,
            "imageURL": "https://tinyimage-prod.moysklad.ru/static/tinyimage/7bf0a89f-c191-11ee-0a80-00d6000033ae/tinyimage/13e7c058-e435-491a-8923-2acd04a73656/t.png",
            "imageURLMiniature": "https://miniature-prod.moysklad.ru/miniature/7bf0a89f-c191-11ee-0a80-00d6000033ae/documentminiature/37cd4cc8-9f5d-427e-87d3-5fb475fe6323",
            "imageURLOriginal": null,
            "price": 820.0,
            "vat": null,
            "currency": "руб",
            "uom": "шт",
            "quantity": 0.0,
            "stock": 0.0,
            "assortmentClass": "com.lognex.onlineorder.model.remap.OnlineOrderVariant",
            "isKit": false,
            "available": true
        },
        {
            "id": "d49951d6-f767-11ef-0a80-0c70000f8d9a",
            "code": "05314",
            "article": null,
            "category": "ЭЛЕКТРОНКИ/MOSMO GT 40000 ( 20 MG )",
            "categoryId": "3f60067a-f767-11ef-0a80-1a36000fe07d",
            "name": "ЭЛ.СИГ. MOSMO GT 40000 2% НИКОТИНА (Манго ананас персик)",
            "description": null,
            "imageURL": "https://tinyimage-prod.moysklad.ru/static/tinyimage/7bf0a89f-c191-11ee-0a80-00d6000033ae/tinyimage/13e7c058-e435-491a-8923-2acd04a73656/t.png",
            "imageURLMiniature": "https://miniature-prod.moysklad.ru/miniature/7bf0a89f-c191-11ee-0a80-00d6000033ae/documentminiature/37cd4cc8-9f5d-427e-87d3-5fb475fe6323",
            "imageURLOriginal": null,
            "price": 820.0,
            "vat": null,
            "currency": "руб",
            "uom": "шт",
            "quantity": 0.0,
            "stock": 0.0,
            "assortmentClass": "com.lognex.onlineorder.model.remap.OnlineOrderVariant",
            "isKit": false,
            "available": true
        },
        {
            "id": "d49c5070-f767-11ef-0a80-0c70000f8da6",
            "code": "05315",
            "article": null,
            "category": "ЭЛЕКТРОНКИ/MOSMO GT 40000 ( 20 MG )",
            "categoryId": "3f60067a-f767-11ef-0a80-1a36000fe07d",
            "name": "ЭЛ.СИГ. MOSMO GT 40000 2% НИКОТИНА (Розовый лимонад банан)",
            "description": null,
            "imageURL": "https://tinyimage-prod.moysklad.ru/static/tinyimage/7bf0a89f-c191-11ee-0a80-00d6000033ae/tinyimage/13e7c058-e435-491a-8923-2acd04a73656/t.png",
            "imageURLMiniature": "https://miniature-prod.moysklad.ru/miniature/7bf0a89f-c191-11ee-0a80-00d6000033ae/documentminiature/37cd4cc8-9f5d-427e-87d3-5fb475fe6323",
            "imageURLOriginal": null,
            "price": 820.0,
            "vat": null,
            "currency": "руб",
            "uom": "шт",
            "quantity": 0.0,
            "stock": 0.0,
            "assortmentClass": "com.lognex.onlineorder.model.remap.OnlineOrderVariant",
            "isKit": false,
            "available": true
        },
        {
            "id": "d49f6f67-f767-11ef-0a80-0c70000f8db2",
            "code": "05316",
            "article": null,
            "category": "ЭЛЕКТРОНКИ/MOSMO GT 40000 ( 20 MG )",
            "categoryId": "3f60067a-f767-11ef-0a80-1a36000fe07d",
            "name": "ЭЛ.СИГ. MOSMO GT 40000 2% НИКОТИНА (Сибирский лимонад)",
            "description": null,
            "imageURL": "https://tinyimage-prod.moysklad.ru/static/tinyimage/7bf0a89f-c191-11ee-0a80-00d6000033ae/tinyimage/13e7c058-e435-491a-8923-2acd04a73656/t.png",
            "imageURLMiniature": "https://miniature-prod.moysklad.ru/miniature/7bf0a89f-c191-11ee-0a80-00d6000033ae/documentminiature/37cd4cc8-9f5d-427e-87d3-5fb475fe6323",
            "imageURLOriginal": null,
            "price": 820.0,
            "vat": null,
            "currency": "руб",
            "uom": "шт",
            "quantity": 0.0,
            "stock": 0.0,
            "assortmentClass": "com.lognex.onlineorder.model.remap.OnlineOrderVariant",
            "isKit": false,
            "available": true
        },
        {
            "id": "d4a2720e-f767-11ef-0a80-0c70000f8dbc",
            "code": "05317",
            "article": null,
            "category": "ЭЛЕКТРОНКИ/MOSMO GT 40000 ( 20 MG )",
            "categoryId": "3f60067a-f767-11ef-0a80-1a36000fe07d",
            "name": "ЭЛ.СИГ. MOSMO GT 40000 2% НИКОТИНА (Фруктовый микс)",
            "description": null,
            "imageURL": "https://tinyimage-prod.moysklad.ru/static/tinyimage/7bf0a89f-c191-11ee-0a80-00d6000033ae/tinyimage/13e7c058-e435-491a-8923-2acd04a73656/t.png",
            "imageURLMiniature": "https://miniature-prod.moysklad.ru/miniature/7bf0a89f-c191-11ee-0a80-00d6000033ae/documentminiature/37cd4cc8-9f5d-427e-87d3-5fb475fe6323",
            "imageURLOriginal": null,
            "price": 820.0,
            "vat": null,
            "currency": "руб",
            "uom": "шт",
            "quantity": 0.0,
            "stock": 0.0,
            "assortmentClass": "com.lognex.onlineorder.model.remap.OnlineOrderVariant",
            "isKit": false,
            "available": true
        },
        {
            "id": "d4a5e171-f767-11ef-0a80-0c70000f8dc6",
            "code": "05318",
            "article": null,
            "category": "ЭЛЕКТРОНКИ/MOSMO GT 40000 ( 20 MG )",
            "categoryId": "3f60067a-f767-11ef-0a80-1a36000fe07d",
            "name": "ЭЛ.СИГ. MOSMO GT 40000 2% НИКОТИНА (Черника малина)",
            "description": null,
            "imageURL": "https://tinyimage-prod.moysklad.ru/static/tinyimage/7bf0a89f-c191-11ee-0a80-00d6000033ae/tinyimage/13e7c058-e435-491a-8923-2acd04a73656/t.png",
            "imageURLMiniature": "https://miniature-prod.moysklad.ru/miniature/7bf0a89f-c191-11ee-0a80-00d6000033ae/documentminiature/37cd4cc8-9f5d-427e-87d3-5fb475fe6323",
            "imageURLOriginal": null,
            "price": 820.0,
            "vat": null,
            "currency": "руб",
            "uom": "шт",
            "quantity": 0.0,
            "stock": 0.0,
            "assortmentClass": "com.lognex.onlineorder.model.remap.OnlineOrderVariant",
            "isKit": false,
            "available": true
        },
        {
            "id": "d4a8c6f2-f767-11ef-0a80-0c70000f8dd0",
            "code": "05319",
            "article": null,
            "category": "ЭЛЕКТРОНКИ/MOSMO GT 40000 ( 20 MG )",
            "categoryId": "3f60067a-f767-11ef-0a80-1a36000fe07d",
            "name": "ЭЛ.СИГ. MOSMO GT 40000 2% НИКОТИНА (Энергетик смородина)",
            "description": null,
            "imageURL": "https://tinyimage-prod.moysklad.ru/static/tinyimage/7bf0a89f-c191-11ee-0a80-00d6000033ae/tinyimage/13e7c058-e435-491a-8923-2acd04a73656/t.png",
            "imageURLMiniature": "https://miniature-prod.moysklad.ru/miniature/7bf0a89f-c191-11ee-0a80-00d6000033ae/documentminiature/37cd4cc8-9f5d-427e-87d3-5fb475fe6323",
            "imageURLOriginal": null,
            "price": 820.0,
            "vat": null,
            "currency": "руб",
            "uom": "шт",
            "quantity": 0.0,
            "stock": 0.0,
            "assortmentClass": "com.lognex.onlineorder.model.remap.OnlineOrderVariant",
            "isKit": false,
            "available": true
        }
    ],
    "size": 21
}