{
    "products": [
        {
            "id": "a52bbe89-eef9-11ef-0a80-017d000129d3",
            "code": "00674",
            "article": null,
            "category": "ЭЛЕКТРОНКИ/PODONKI 10.000 ( 50 MG )",
            "categoryId": "59752297-eef9-11ef-0a80-08550001241d",
            "name": "ЭЛ.СИГ.  PODONKI 10.000 5% НИКОТИНА",
            "description": null,
            "imageURL": "https://tinyimage-prod.moysklad.ru/static/tinyimage/7bf0a89f-c191-11ee-0a80-00d6000033ae/tinyimage/6c4e102c-5fad-4276-a2f4-e6d30c13634f/t.png",
            "imageURLMiniature": "https://miniature-prod.moysklad.ru/miniature/7bf0a89f-c191-11ee-0a80-00d6000033ae/documentminiature/f6c51e99-9062-49b5-a537-060f6e1fc6b6",
            "imageURLOriginal": null,
            "price": 470.0,
            "vat": null,
            "currency": "руб",
            "uom": "шт",
            "quantity": 0.0,
            "stock": 0.0,
            "assortmentClass": "com.lognex.onlineorder.model.remap.OnlineOrderProduct",
            "isKit": false,
            "available": true
        },
        {
            "id": "08578a2d-eefa-11ef-0a80-04c7000106e1",
            "code": "05153",
            "article": null,
            "category": "ЭЛЕКТРОНКИ/PODONKI 10.000 ( 50 MG )",
            "categoryId": "59752297-eef9-11ef-0a80-08550001241d",
            "name": "ЭЛ.СИГ.  PODONKI 10.000 5% НИКОТИНА (АНАНАСОВОЕ КОКОСОВОЕ  МОЛОКО)",
            "description": null,
            "imageURL": "https://tinyimage-prod.moysklad.ru/static/tinyimage/7bf0a89f-c191-11ee-0a80-00d6000033ae/tinyimage/6c4e102c-5fad-4276-a2f4-e6d30c13634f/t.png",
            "imageURLMiniature": "https://miniature-prod.moysklad.ru/miniature/7bf0a89f-c191-11ee-0a80-00d6000033ae/documentminiature/f6c51e99-9062-49b5-a537-060f6e1fc6b6",
            "imageURLOriginal": null,
            "price": 470.0,
            "vat": null,
            "currency": "руб",
            "uom": "шт",
            "quantity": 0.0,
            "stock": 0.0,
            "assortmentClass": "com.lognex.onlineorder.model.remap.OnlineOrderVariant",
            "isKit": false,
            "available": true
        },
        {
            "id": "085d948c-eefa-11ef-0a80-04c7000106eb",
            "code": "05154",
            "article": null,
            "category": "ЭЛЕКТРОНКИ/PODONKI 10.000 ( 50 MG )",
            "categoryId": "59752297-eef9-11ef-0a80-08550001241d",
            "name": "ЭЛ.СИГ.  PODONKI 10.000 5% НИКОТИНА (ВИШНЕВО БАНАНОВЫЙ ЛЕД)",
            "description": null,
            "imageURL": "https://tinyimage-prod.moysklad.ru/static/tinyimage/7bf0a89f-c191-11ee-0a80-00d6000033ae/tinyimage/6c4e102c-5fad-4276-a2f4-e6d30c13634f/t.png",
            "imageURLMiniature": "https://miniature-prod.moysklad.ru/miniature/7bf0a89f-c191-11ee-0a80-00d6000033ae/documentminiature/f6c51e99-9062-49b5-a537-060f6e1fc6b6",
            "imageURLOriginal": null,
            "price": 470.0,
            "vat": null,
            "currency": "руб",
            "uom": "шт",
            "quantity": 0.0,
            "stock": 0.0,
            "assortmentClass": "com.lognex.onlineorder.model.remap.OnlineOrderVariant",
            "isKit": false,
            "available": true
        },
        {
            "id": "08611f72-eefa-11ef-0a80-04c7000106f5",
            "code": "05155",
            "article": null,
            "category": "ЭЛЕКТРОНКИ/PODONKI 10.000 ( 50 MG )",
            "categoryId": "59752297-eef9-11ef-0a80-08550001241d",
            "name": "ЭЛ.СИГ.  PODONKI 10.000 5% НИКОТИНА (КИВИ ГУАВА МАРАКУЙЯ)",
            "description": null,
            "imageURL": "https://tinyimage-prod.moysklad.ru/static/tinyimage/7bf0a89f-c191-11ee-0a80-00d6000033ae/tinyimage/6c4e102c-5fad-4276-a2f4-e6d30c13634f/t.png",
            "imageURLMiniature": "https://miniature-prod.moysklad.ru/miniature/7bf0a89f-c191-11ee-0a80-00d6000033ae/documentminiature/f6c51e99-9062-49b5-a537-060f6e1fc6b6",
            "imageURLOriginal": null,
            "price": 470.0,
            "vat": null,
            "currency": "руб",
            "uom": "шт",
            "quantity": 0.0,
            "stock": 0.0,
            "assortmentClass": "com.lognex.onlineorder.model.remap.OnlineOrderVariant",
            "isKit": false,
            "available": true
        },
        {
            "id": "08651aa9-eefa-11ef-0a80-04c7000106ff",
            "code": "05156",
            "article": null,
            "category": "ЭЛЕКТРОНКИ/PODONKI 10.000 ( 50 MG )",
            "categoryId": "59752297-eef9-11ef-0a80-08550001241d",
            "name": "ЭЛ.СИГ.  PODONKI 10.000 5% НИКОТИНА (КИВИ ЯБЛОКО РЕДБУЛЛ)",
            "description": null,
            "imageURL": "https://tinyimage-prod.moysklad.ru/static/tinyimage/7bf0a89f-c191-11ee-0a80-00d6000033ae/tinyimage/6c4e102c-5fad-4276-a2f4-e6d30c13634f/t.png",
            "imageURLMiniature": "https://miniature-prod.moysklad.ru/miniature/7bf0a89f-c191-11ee-0a80-00d6000033ae/documentminiature/f6c51e99-9062-49b5-a537-060f6e1fc6b6",
            "imageURLOriginal": null,
            "price": 470.0,
            "vat": null,
            "currency": "руб",
            "uom": "шт",
            "quantity": 0.0,
            "stock": 0.0,
            "assortmentClass": "com.lognex.onlineorder.model.remap.OnlineOrderVariant",
            "isKit": false,
            "available": true
        },
        {
            "id": "0868d598-eefa-11ef-0a80-04c700010709",
            "code": "05157",
            "article": null,
            "category": "ЭЛЕКТРОНКИ/PODONKI 10.000 ( 50 MG )",
            "categoryId": "59752297-eef9-11ef-0a80-08550001241d",
            "name": "ЭЛ.СИГ.  PODONKI 10.000 5% НИКОТИНА (КЛУБНИКА КИВИ)",
            "description": null,
            "imageURL": "https://tinyimage-prod.moysklad.ru/static/tinyimage/7bf0a89f-c191-11ee-0a80-00d6000033ae/tinyimage/6c4e102c-5fad-4276-a2f4-e6d30c13634f/t.png",
            "imageURLMiniature": "https://miniature-prod.moysklad.ru/miniature/7bf0a89f-c191-11ee-0a80-00d6000033ae/documentminiature/f6c51e99-9062-49b5-a537-060f6e1fc6b6",
            "imageURLOriginal": null,
            "price": 470.0,
            "vat": null,
            "currency": "руб",
            "uom": "шт",
            "quantity": 0.0,
            "stock": 0.0,
            "assortmentClass": "com.lognex.onlineorder.model.remap.OnlineOrderVariant",
            "isKit": false,
            "available": true
        },
        {
            "id": "086cc423-eefa-11ef-0a80-04c700010713",
            "code": "05158",
            "article": null,
            "category": "ЭЛЕКТРОНКИ/PODONKI 10.000 ( 50 MG )",
            "categoryId": "59752297-eef9-11ef-0a80-08550001241d",
            "name": "ЭЛ.СИГ.  PODONKI 10.000 5% НИКОТИНА (КЛУБНИКА КОКОС)",
            "description": null,
            "imageURL": "https://tinyimage-prod.moysklad.ru/static/tinyimage/7bf0a89f-c191-11ee-0a80-00d6000033ae/tinyimage/6c4e102c-5fad-4276-a2f4-e6d30c13634f/t.png",
            "imageURLMiniature": "https://miniature-prod.moysklad.ru/miniature/7bf0a89f-c191-11ee-0a80-00d6000033ae/documentminiature/f6c51e99-9062-49b5-a537-060f6e1fc6b6",
            "imageURLOriginal": null,
            "price": 470.0,
            "vat": null,
            "currency": "руб",
            "uom": "шт",
            "quantity": 0.0,
            "stock": 0.0,
            "assortmentClass": "com.lognex.onlineorder.model.remap.OnlineOrderVariant",
            "isKit": false,
            "available": true
        },
        {
            "id": "086ffe62-eefa-11ef-0a80-04c70001071d",
            "code": "05159",
            "article": null,
            "category": "ЭЛЕКТРОНКИ/PODONKI 10.000 ( 50 MG )",
            "categoryId": "59752297-eef9-11ef-0a80-08550001241d",
            "name": "ЭЛ.СИГ.  PODONKI 10.000 5% НИКОТИНА (КЛУБНИЧНОЕ МОРОЖЕНОЕ)",
            "description": null,
            "imageURL": "https://tinyimage-prod.moysklad.ru/static/tinyimage/7bf0a89f-c191-11ee-0a80-00d6000033ae/tinyimage/6c4e102c-5fad-4276-a2f4-e6d30c13634f/t.png",
            "imageURLMiniature": "https://miniature-prod.moysklad.ru/miniature/7bf0a89f-c191-11ee-0a80-00d6000033ae/documentminiature/f6c51e99-9062-49b5-a537-060f6e1fc6b6",
            "imageURLOriginal": null,
            "price": 470.0,
            "vat": null,
            "currency": "руб",
            "uom": "шт",
            "quantity": 0.0,
            "stock": 0.0,
            "assortmentClass": "com.lognex.onlineorder.model.remap.OnlineOrderVariant",
            "isKit": false,
            "available": true
        },
        {
            "id": "0872f926-eefa-11ef-0a80-04c700010727",
            "code": "05160",
            "article": null,
            "category": "ЭЛЕКТРОНКИ/PODONKI 10.000 ( 50 MG )",
            "categoryId": "59752297-eef9-11ef-0a80-08550001241d",
            "name": "ЭЛ.СИГ.  PODONKI 10.000 5% НИКОТИНА (ЛЕДЯНАЯ ЧЕРНИКА)",
            "description": null,
            "imageURL": "https://tinyimage-prod.moysklad.ru/static/tinyimage/7bf0a89f-c191-11ee-0a80-00d6000033ae/tinyimage/6c4e102c-5fad-4276-a2f4-e6d30c13634f/t.png",
            "imageURLMiniature": "https://miniature-prod.moysklad.ru/miniature/7bf0a89f-c191-11ee-0a80-00d6000033ae/documentminiature/f6c51e99-9062-49b5-a537-060f6e1fc6b6",
            "imageURLOriginal": null,
            "price": 470.0,
            "vat": null,
            "currency": "руб",
            "uom": "шт",
            "quantity": 0.0,
            "stock": 0.0,
            "assortmentClass": "com.lognex.onlineorder.model.remap.OnlineOrderVariant",
            "isKit": false,
            "available": true
        },
        {
            "id": "087717d2-eefa-11ef-0a80-04c700010731",
            "code": "05161",
            "article": null,
            "category": "ЭЛЕКТРОНКИ/PODONKI 10.000 ( 50 MG )",
            "categoryId": "59752297-eef9-11ef-0a80-08550001241d",
            "name": "ЭЛ.СИГ.  PODONKI 10.000 5% НИКОТИНА (ЛЕДЯНОЕ МАНГО)",
            "description": null,
            "imageURL": "https://tinyimage-prod.moysklad.ru/static/tinyimage/7bf0a89f-c191-11ee-0a80-00d6000033ae/tinyimage/6c4e102c-5fad-4276-a2f4-e6d30c13634f/t.png",
            "imageURLMiniature": "https://miniature-prod.moysklad.ru/miniature/7bf0a89f-c191-11ee-0a80-00d6000033ae/documentminiature/f6c51e99-9062-49b5-a537-060f6e1fc6b6",
            "imageURLOriginal": null,
            "price": 470.0,
            "vat": null,
            "currency": "руб",
            "uom": "шт",
            "quantity": 0.0,
            "stock": 0.0,
            "assortmentClass": "com.lognex.onlineorder.model.remap.OnlineOrderVariant",
            "isKit": false,
            "available": true
        },
        {
            "id": "087b835d-eefa-11ef-0a80-04c70001073b",
            "code": "05162",
            "article": null,
            "category": "ЭЛЕКТРОНКИ/PODONKI 10.000 ( 50 MG )",
            "categoryId": "59752297-eef9-11ef-0a80-08550001241d",
            "name": "ЭЛ.СИГ.  PODONKI 10.000 5% НИКОТИНА (ЛЕДЯНОЙ АРБУЗ)",
            "description": null,
            "imageURL": "https://tinyimage-prod.moysklad.ru/static/tinyimage/7bf0a89f-c191-11ee-0a80-00d6000033ae/tinyimage/6c4e102c-5fad-4276-a2f4-e6d30c13634f/t.png",
            "imageURLMiniature": "https://miniature-prod.moysklad.ru/miniature/7bf0a89f-c191-11ee-0a80-00d6000033ae/documentminiature/f6c51e99-9062-49b5-a537-060f6e1fc6b6",
            "imageURLOriginal": null,
            "price": 470.0,
            "vat": null,
            "currency": "руб",
            "uom": "шт",
            "quantity": 0.0,
            "stock": 0.0,
            "assortmentClass": "com.lognex.onlineorder.model.remap.OnlineOrderVariant",
            "isKit": false,
            "available": true
        },
        {
            "id": "087fe8fe-eefa-11ef-0a80-04c700010745",
            "code": "05163",
            "article": null,
            "category": "ЭЛЕКТРОНКИ/PODONKI 10.000 ( 50 MG )",
            "categoryId": "59752297-eef9-11ef-0a80-08550001241d",
            "name": "ЭЛ.СИГ.  PODONKI 10.000 5% НИКОТИНА (ЛЕДЯНОЙ ВИНОГРАД)",
            "description": null,
            "imageURL": "https://tinyimage-prod.moysklad.ru/static/tinyimage/7bf0a89f-c191-11ee-0a80-00d6000033ae/tinyimage/6c4e102c-5fad-4276-a2f4-e6d30c13634f/t.png",
            "imageURLMiniature": "https://miniature-prod.moysklad.ru/miniature/7bf0a89f-c191-11ee-0a80-00d6000033ae/documentminiature/f6c51e99-9062-49b5-a537-060f6e1fc6b6",
            "imageURLOriginal": null,
            "price": 470.0,
            "vat": null,
            "currency": "руб",
            "uom": "шт",
            "quantity": 0.0,
            "stock": 0.0,
            "assortmentClass": "com.lognex.onlineorder.model.remap.OnlineOrderVariant",
            "isKit": false,
            "available": true
        },
        {
            "id": "0884111e-eefa-11ef-0a80-04c70001074f",
            "code": "05164",
            "article": null,
            "category": "ЭЛЕКТРОНКИ/PODONKI 10.000 ( 50 MG )",
            "categoryId": "59752297-eef9-11ef-0a80-08550001241d",
            "name": "ЭЛ.СИГ.  PODONKI 10.000 5% НИКОТИНА (МАРАКУЙЯ МАНГО)",
            "description": null,
            "imageURL": "https://tinyimage-prod.moysklad.ru/static/tinyimage/7bf0a89f-c191-11ee-0a80-00d6000033ae/tinyimage/6c4e102c-5fad-4276-a2f4-e6d30c13634f/t.png",
            "imageURLMiniature": "https://miniature-prod.moysklad.ru/miniature/7bf0a89f-c191-11ee-0a80-00d6000033ae/documentminiature/f6c51e99-9062-49b5-a537-060f6e1fc6b6",
            "imageURLOriginal": null,
            "price": 470.0,
            "vat": null,
            "currency": "руб",
            "uom": "шт",
            "quantity": 0.0,
            "stock": 0.0,
            "assortmentClass": "com.lognex.onlineorder.model.remap.OnlineOrderVariant",
            "isKit": false,
            "available": true
        },
        {
            "id": "0888220a-eefa-11ef-0a80-04c700010759",
            "code": "05165",
            "article": null,
            "category": "ЭЛЕКТРОНКИ/PODONKI 10.000 ( 50 MG )",
            "categoryId": "59752297-eef9-11ef-0a80-08550001241d",
            "name": "ЭЛ.СИГ.  PODONKI 10.000 5% НИКОТИНА (МАРМЕЛАДНЫЕ МИШКИ)",
            "description": null,
            "imageURL": "https://tinyimage-prod.moysklad.ru/static/tinyimage/7bf0a89f-c191-11ee-0a80-00d6000033ae/tinyimage/6c4e102c-5fad-4276-a2f4-e6d30c13634f/t.png",
            "imageURLMiniature": "https://miniature-prod.moysklad.ru/miniature/7bf0a89f-c191-11ee-0a80-00d6000033ae/documentminiature/f6c51e99-9062-49b5-a537-060f6e1fc6b6",
            "imageURLOriginal": null,
            "price": 470.0,
            "vat": null,
            "currency": "руб",
            "uom": "шт",
            "quantity": 0.0,
            "stock": 0.0,
            "assortmentClass": "com.lognex.onlineorder.model.remap.OnlineOrderVariant",
            "isKit": false,
            "available": true
        },
        {
            "id": "088f970a-eefa-11ef-0a80-04c700010763",
            "code": "05166",
            "article": null,
            "category": "ЭЛЕКТРОНКИ/PODONKI 10.000 ( 50 MG )",
            "categoryId": "59752297-eef9-11ef-0a80-08550001241d",
            "name": "ЭЛ.СИГ.  PODONKI 10.000 5% НИКОТИНА (МЕДОВЫЙ ПЕРСИК АПЕЛЬСИН)",
            "description": null,
            "imageURL": "https://tinyimage-prod.moysklad.ru/static/tinyimage/7bf0a89f-c191-11ee-0a80-00d6000033ae/tinyimage/6c4e102c-5fad-4276-a2f4-e6d30c13634f/t.png",
            "imageURLMiniature": "https://miniature-prod.moysklad.ru/miniature/7bf0a89f-c191-11ee-0a80-00d6000033ae/documentminiature/f6c51e99-9062-49b5-a537-060f6e1fc6b6",
            "imageURLOriginal": null,
            "price": 470.0,
            "vat": null,
            "currency": "руб",
            "uom": "шт",
            "quantity": 0.0,
            "stock": 0.0,
            "assortmentClass": "com.lognex.onlineorder.model.remap.OnlineOrderVariant",
            "isKit": false,
            "available": true
        },
        {
            "id": "0893d752-eefa-11ef-0a80-04c70001076d",
            "code": "05167",
            "article": null,
            "category": "ЭЛЕКТРОНКИ/PODONKI 10.000 ( 50 MG )",
            "categoryId": "59752297-eef9-11ef-0a80-08550001241d",
            "name": "ЭЛ.СИГ.  PODONKI 10.000 5% НИКОТИНА (ТРОПИЧЕСКИЕ ФРУКТЫ)",
            "description": null,
            "imageURL": "https://tinyimage-prod.moysklad.ru/static/tinyimage/7bf0a89f-c191-11ee-0a80-00d6000033ae/tinyimage/6c4e102c-5fad-4276-a2f4-e6d30c13634f/t.png",
            "imageURLMiniature": "https://miniature-prod.moysklad.ru/miniature/7bf0a89f-c191-11ee-0a80-00d6000033ae/documentminiature/f6c51e99-9062-49b5-a537-060f6e1fc6b6",
            "imageURLOriginal": null,
            "price": 470.0,
            "vat": null,
            "currency": "руб",
            "uom": "шт",
            "quantity": 0.0,
            "stock": 0.0,
            "assortmentClass": "com.lognex.onlineorder.model.remap.OnlineOrderVariant",
            "isKit": false,
            "available": true
        },
        {
            "id": "08975ae6-eefa-11ef-0a80-04c700010777",
            "code": "05168",
            "article": null,
            "category": "ЭЛЕКТРОНКИ/PODONKI 10.000 ( 50 MG )",
            "categoryId": "59752297-eef9-11ef-0a80-08550001241d",
            "name": "ЭЛ.СИГ.  PODONKI 10.000 5% НИКОТИНА (ФАНТА КОЛА СО ЛЬДОМ)",
            "description": null,
            "imageURL": "https://tinyimage-prod.moysklad.ru/static/tinyimage/7bf0a89f-c191-11ee-0a80-00d6000033ae/tinyimage/6c4e102c-5fad-4276-a2f4-e6d30c13634f/t.png",
            "imageURLMiniature": "https://miniature-prod.moysklad.ru/miniature/7bf0a89f-c191-11ee-0a80-00d6000033ae/documentminiature/f6c51e99-9062-49b5-a537-060f6e1fc6b6",
            "imageURLOriginal": null,
            "price": 470.0,
            "vat": null,
            "currency": "руб",
            "uom": "шт",
            "quantity": 0.0,
            "stock": 0.0,
            "assortmentClass": "com.lognex.onlineorder.model.remap.OnlineOrderVariant",
            "isKit": false,
            "available": true
        },
        {
            "id": "089b0377-eefa-11ef-0a80-04c700010781",
            "code": "05169",
            "article": null,
            "category": "ЭЛЕКТРОНКИ/PODONKI 10.000 ( 50 MG )",
            "categoryId": "59752297-eef9-11ef-0a80-08550001241d",
            "name": "ЭЛ.СИГ.  PODONKI 10.000 5% НИКОТИНА (ЧЕРНИКА ВИШНЯ)",
            "description": null,
            "imageURL": "https://tinyimage-prod.moysklad.ru/static/tinyimage/7bf0a89f-c191-11ee-0a80-00d6000033ae/tinyimage/6c4e102c-5fad-4276-a2f4-e6d30c13634f/t.png",
            "imageURLMiniature": "https://miniature-prod.moysklad.ru/miniature/7bf0a89f-c191-11ee-0a80-00d6000033ae/documentminiature/f6c51e99-9062-49b5-a537-060f6e1fc6b6",
            "imageURLOriginal": null,
            "price": 470.0,
            "vat": null,
            "currency": "руб",
            "uom": "шт",
            "quantity": 0.0,
            "stock": 0.0,
            "assortmentClass": "com.lognex.onlineorder.model.remap.OnlineOrderVariant",
            "isKit": false,
            "available": true
        },
        {
            "id": "089ecb08-eefa-11ef-0a80-04c70001078b",
            "code": "05170",
            "article": null,
            "category": "ЭЛЕКТРОНКИ/PODONKI 10.000 ( 50 MG )",
            "categoryId": "59752297-eef9-11ef-0a80-08550001241d",
            "name": "ЭЛ.СИГ.  PODONKI 10.000 5% НИКОТИНА (ЧЕРНИЧНО-ВИШНЕВЫЙ СОК)",
            "description": null,
            "imageURL": "https://tinyimage-prod.moysklad.ru/static/tinyimage/7bf0a89f-c191-11ee-0a80-00d6000033ae/tinyimage/6c4e102c-5fad-4276-a2f4-e6d30c13634f/t.png",
            "imageURLMiniature": "https://miniature-prod.moysklad.ru/miniature/7bf0a89f-c191-11ee-0a80-00d6000033ae/documentminiature/f6c51e99-9062-49b5-a537-060f6e1fc6b6",
            "imageURLOriginal": null,
            "price": 470.0,
            "vat": null,
            "currency": "руб",
            "uom": "шт",
            "quantity": 0.0,
            "stock": 0.0,
            "assortmentClass": "com.lognex.onlineorder.model.remap.OnlineOrderVariant",
            "isKit": false,
            "available": true
        },
        {
            "id": "08a29dbc-eefa-11ef-0a80-04c700010795",
            "code": "05171",
            "article": null,
            "category": "ЭЛЕКТРОНКИ/PODONKI 10.000 ( 50 MG )",
            "categoryId": "59752297-eef9-11ef-0a80-08550001241d",
            "name": "ЭЛ.СИГ.  PODONKI 10.000 5% НИКОТИНА (ЧЕРНИЧНО-МАЛИНОВЫЙ  ЛИМОНАД)",
            "description": null,
            "imageURL": "https://tinyimage-prod.moysklad.ru/static/tinyimage/7bf0a89f-c191-11ee-0a80-00d6000033ae/tinyimage/6c4e102c-5fad-4276-a2f4-e6d30c13634f/t.png",
            "imageURLMiniature": "https://miniature-prod.moysklad.ru/miniature/7bf0a89f-c191-11ee-0a80-00d6000033ae/documentminiature/f6c51e99-9062-49b5-a537-060f6e1fc6b6",
            "imageURLOriginal": null,
            "price": 470.0,
            "vat": null,
            "currency": "руб",
            "uom": "шт",
            "quantity": 0.0,
            "stock": 0.0,
            "assortmentClass": "com.lognex.onlineorder.model.remap.OnlineOrderVariant",
            "isKit": false,
            "available": true
        },
        {
            "id": "08a6c8b0-eefa-11ef-0a80-04c70001079f",
            "code": "05172",
            "article": null,
            "category": "ЭЛЕКТРОНКИ/PODONKI 10.000 ( 50 MG )",
            "categoryId": "59752297-eef9-11ef-0a80-08550001241d",
            "name": "ЭЛ.СИГ.  PODONKI 10.000 5% НИКОТИНА (ЯПОНСКИЙ ЧАЙ)",
            "description": null,
            "imageURL": "https://tinyimage-prod.moysklad.ru/static/tinyimage/7bf0a89f-c191-11ee-0a80-00d6000033ae/tinyimage/6c4e102c-5fad-4276-a2f4-e6d30c13634f/t.png",
            "imageURLMiniature": "https://miniature-prod.moysklad.ru/miniature/7bf0a89f-c191-11ee-0a80-00d6000033ae/documentminiature/f6c51e99-9062-49b5-a537-060f6e1fc6b6",
            "imageURLOriginal": null,
            "price": 470.0,
            "vat": null,
            "currency": "руб",
            "uom": "шт",
            "quantity": 0.0,
            "stock": 0.0,
            "assortmentClass": "com.lognex.onlineorder.model.remap.OnlineOrderVariant",
            "isKit": false,
            "available": true
        }
    ],
    "size": 21
}