{
    "products": [
        {
            "id": "6cee69a9-3319-11f0-0a80-055a002f265b",
            "code": "00740",
            "article": null,
            "category": "ЭЛЕКТРОНКИ/SNOOPY SMOKE 40.000 ( 50 MG )",
            "categoryId": "6312fd42-3319-11f0-0a80-0f86002ea137",
            "name": "ЭЛ. СИГ. SNOOPY SMOKE 40.000 5% НИКОТИНА",
            "description": null,
            "imageURL": "https://tinyimage-prod.moysklad.ru/static/tinyimage/7bf0a89f-c191-11ee-0a80-00d6000033ae/tinyimage/1438d84c-690c-4eea-be02-8f0c95dd6136/t.png",
            "imageURLMiniature": "https://miniature-prod.moysklad.ru/miniature/7bf0a89f-c191-11ee-0a80-00d6000033ae/documentminiature/3b542cc0-63fc-4d6b-aabe-5e93b63105ad",
            "imageURLOriginal": null,
            "price": 570.0,
            "vat": null,
            "currency": "руб",
            "uom": "шт",
            "quantity": 0.0,
            "stock": 0.0,
            "assortmentClass": "com.lognex.onlineorder.model.remap.OnlineOrderProduct",
            "isKit": false,
            "available": true
        },
        {
            "id": "f7d98471-3319-11f0-0a80-19c5002e055e",
            "code": "05892",
            "article": null,
            "category": "ЭЛЕКТРОНКИ/SNOOPY SMOKE 40.000 ( 50 MG )",
            "categoryId": "6312fd42-3319-11f0-0a80-0f86002ea137",
            "name": "ЭЛ. СИГ. SNOOPY SMOKE 40.000 5% НИКОТИНА (BAHAMA MAMA)",
            "description": null,
            "imageURL": "https://tinyimage-prod.moysklad.ru/static/tinyimage/7bf0a89f-c191-11ee-0a80-00d6000033ae/tinyimage/1438d84c-690c-4eea-be02-8f0c95dd6136/t.png",
            "imageURLMiniature": "https://miniature-prod.moysklad.ru/miniature/7bf0a89f-c191-11ee-0a80-00d6000033ae/documentminiature/3b542cc0-63fc-4d6b-aabe-5e93b63105ad",
            "imageURLOriginal": null,
            "price": 570.0,
            "vat": null,
            "currency": "руб",
            "uom": "шт",
            "quantity": 0.0,
            "stock": 0.0,
            "assortmentClass": "com.lognex.onlineorder.model.remap.OnlineOrderVariant",
            "isKit": false,
            "available": true
        },
        {
            "id": "f7de6d49-3319-11f0-0a80-19c5002e0569",
            "code": "05893",
            "article": null,
            "category": "ЭЛЕКТРОНКИ/SNOOPY SMOKE 40.000 ( 50 MG )",
            "categoryId": "6312fd42-3319-11f0-0a80-0f86002ea137",
            "name": "ЭЛ. СИГ. SNOOPY SMOKE 40.000 5% НИКОТИНА (LUSCH ICE)",
            "description": null,
            "imageURL": "https://tinyimage-prod.moysklad.ru/static/tinyimage/7bf0a89f-c191-11ee-0a80-00d6000033ae/tinyimage/1438d84c-690c-4eea-be02-8f0c95dd6136/t.png",
            "imageURLMiniature": "https://miniature-prod.moysklad.ru/miniature/7bf0a89f-c191-11ee-0a80-00d6000033ae/documentminiature/3b542cc0-63fc-4d6b-aabe-5e93b63105ad",
            "imageURLOriginal": null,
            "price": 570.0,
            "vat": null,
            "currency": "руб",
            "uom": "шт",
            "quantity": 0.0,
            "stock": 0.0,
            "assortmentClass": "com.lognex.onlineorder.model.remap.OnlineOrderVariant",
            "isKit": false,
            "available": true
        },
        {
            "id": "f7e2130b-3319-11f0-0a80-19c5002e0573",
            "code": "05894",
            "article": null,
            "category": "ЭЛЕКТРОНКИ/SNOOPY SMOKE 40.000 ( 50 MG )",
            "categoryId": "6312fd42-3319-11f0-0a80-0f86002ea137",
            "name": "ЭЛ. СИГ. SNOOPY SMOKE 40.000 5% НИКОТИНА (АНАНАС ЛЕД)",
            "description": null,
            "imageURL": "https://tinyimage-prod.moysklad.ru/static/tinyimage/7bf0a89f-c191-11ee-0a80-00d6000033ae/tinyimage/1438d84c-690c-4eea-be02-8f0c95dd6136/t.png",
            "imageURLMiniature": "https://miniature-prod.moysklad.ru/miniature/7bf0a89f-c191-11ee-0a80-00d6000033ae/documentminiature/3b542cc0-63fc-4d6b-aabe-5e93b63105ad",
            "imageURLOriginal": null,
            "price": 570.0,
            "vat": null,
            "currency": "руб",
            "uom": "шт",
            "quantity": 0.0,
            "stock": 0.0,
            "assortmentClass": "com.lognex.onlineorder.model.remap.OnlineOrderVariant",
            "isKit": false,
            "available": true
        },
        {
            "id": "f7e5836b-3319-11f0-0a80-19c5002e057d",
            "code": "05895",
            "article": null,
            "category": "ЭЛЕКТРОНКИ/SNOOPY SMOKE 40.000 ( 50 MG )",
            "categoryId": "6312fd42-3319-11f0-0a80-0f86002ea137",
            "name": "ЭЛ. СИГ. SNOOPY SMOKE 40.000 5% НИКОТИНА (АРБУЗ ЛЕД)",
            "description": null,
            "imageURL": "https://tinyimage-prod.moysklad.ru/static/tinyimage/7bf0a89f-c191-11ee-0a80-00d6000033ae/tinyimage/1438d84c-690c-4eea-be02-8f0c95dd6136/t.png",
            "imageURLMiniature": "https://miniature-prod.moysklad.ru/miniature/7bf0a89f-c191-11ee-0a80-00d6000033ae/documentminiature/3b542cc0-63fc-4d6b-aabe-5e93b63105ad",
            "imageURLOriginal": null,
            "price": 570.0,
            "vat": null,
            "currency": "руб",
            "uom": "шт",
            "quantity": 0.0,
            "stock": 0.0,
            "assortmentClass": "com.lognex.onlineorder.model.remap.OnlineOrderVariant",
            "isKit": false,
            "available": true
        },
        {
            "id": "f7e9828e-3319-11f0-0a80-19c5002e0587",
            "code": "05896",
            "article": null,
            "category": "ЭЛЕКТРОНКИ/SNOOPY SMOKE 40.000 ( 50 MG )",
            "categoryId": "6312fd42-3319-11f0-0a80-0f86002ea137",
            "name": "ЭЛ. СИГ. SNOOPY SMOKE 40.000 5% НИКОТИНА (ВИНОГРАД ЛЕД)",
            "description": null,
            "imageURL": "https://tinyimage-prod.moysklad.ru/static/tinyimage/7bf0a89f-c191-11ee-0a80-00d6000033ae/tinyimage/1438d84c-690c-4eea-be02-8f0c95dd6136/t.png",
            "imageURLMiniature": "https://miniature-prod.moysklad.ru/miniature/7bf0a89f-c191-11ee-0a80-00d6000033ae/documentminiature/3b542cc0-63fc-4d6b-aabe-5e93b63105ad",
            "imageURLOriginal": null,
            "price": 570.0,
            "vat": null,
            "currency": "руб",
            "uom": "шт",
            "quantity": 0.0,
            "stock": 0.0,
            "assortmentClass": "com.lognex.onlineorder.model.remap.OnlineOrderVariant",
            "isKit": false,
            "available": true
        },
        {
            "id": "f7ee083c-3319-11f0-0a80-19c5002e0591",
            "code": "05897",
            "article": null,
            "category": "ЭЛЕКТРОНКИ/SNOOPY SMOKE 40.000 ( 50 MG )",
            "categoryId": "6312fd42-3319-11f0-0a80-0f86002ea137",
            "name": "ЭЛ. СИГ. SNOOPY SMOKE 40.000 5% НИКОТИНА (ВИШНЕВАЯ КОЛА)",
            "description": null,
            "imageURL": "https://tinyimage-prod.moysklad.ru/static/tinyimage/7bf0a89f-c191-11ee-0a80-00d6000033ae/tinyimage/1438d84c-690c-4eea-be02-8f0c95dd6136/t.png",
            "imageURLMiniature": "https://miniature-prod.moysklad.ru/miniature/7bf0a89f-c191-11ee-0a80-00d6000033ae/documentminiature/3b542cc0-63fc-4d6b-aabe-5e93b63105ad",
            "imageURLOriginal": null,
            "price": 570.0,
            "vat": null,
            "currency": "руб",
            "uom": "шт",
            "quantity": 0.0,
            "stock": 0.0,
            "assortmentClass": "com.lognex.onlineorder.model.remap.OnlineOrderVariant",
            "isKit": false,
            "available": true
        },
        {
            "id": "f7f17554-3319-11f0-0a80-19c5002e059b",
            "code": "05898",
            "article": null,
            "category": "ЭЛЕКТРОНКИ/SNOOPY SMOKE 40.000 ( 50 MG )",
            "categoryId": "6312fd42-3319-11f0-0a80-0f86002ea137",
            "name": "ЭЛ. СИГ. SNOOPY SMOKE 40.000 5% НИКОТИНА (КЛУБНИКА БАНАН)",
            "description": null,
            "imageURL": "https://tinyimage-prod.moysklad.ru/static/tinyimage/7bf0a89f-c191-11ee-0a80-00d6000033ae/tinyimage/1438d84c-690c-4eea-be02-8f0c95dd6136/t.png",
            "imageURLMiniature": "https://miniature-prod.moysklad.ru/miniature/7bf0a89f-c191-11ee-0a80-00d6000033ae/documentminiature/3b542cc0-63fc-4d6b-aabe-5e93b63105ad",
            "imageURLOriginal": null,
            "price": 570.0,
            "vat": null,
            "currency": "руб",
            "uom": "шт",
            "quantity": 0.0,
            "stock": 0.0,
            "assortmentClass": "com.lognex.onlineorder.model.remap.OnlineOrderVariant",
            "isKit": false,
            "available": true
        },
        {
            "id": "f7f4d6f0-3319-11f0-0a80-19c5002e05a5",
            "code": "05899",
            "article": null,
            "category": "ЭЛЕКТРОНКИ/SNOOPY SMOKE 40.000 ( 50 MG )",
            "categoryId": "6312fd42-3319-11f0-0a80-0f86002ea137",
            "name": "ЭЛ. СИГ. SNOOPY SMOKE 40.000 5% НИКОТИНА (КЛУБНИКА КИВИ)",
            "description": null,
            "imageURL": "https://tinyimage-prod.moysklad.ru/static/tinyimage/7bf0a89f-c191-11ee-0a80-00d6000033ae/tinyimage/1438d84c-690c-4eea-be02-8f0c95dd6136/t.png",
            "imageURLMiniature": "https://miniature-prod.moysklad.ru/miniature/7bf0a89f-c191-11ee-0a80-00d6000033ae/documentminiature/3b542cc0-63fc-4d6b-aabe-5e93b63105ad",
            "imageURLOriginal": null,
            "price": 570.0,
            "vat": null,
            "currency": "руб",
            "uom": "шт",
            "quantity": 0.0,
            "stock": 0.0,
            "assortmentClass": "com.lognex.onlineorder.model.remap.OnlineOrderVariant",
            "isKit": false,
            "available": true
        },
        {
            "id": "f7f7fbfc-3319-11f0-0a80-19c5002e05af",
            "code": "05900",
            "article": null,
            "category": "ЭЛЕКТРОНКИ/SNOOPY SMOKE 40.000 ( 50 MG )",
            "categoryId": "6312fd42-3319-11f0-0a80-0f86002ea137",
            "name": "ЭЛ. СИГ. SNOOPY SMOKE 40.000 5% НИКОТИНА (КЛУБНИКА ЛЕД)",
            "description": null,
            "imageURL": "https://tinyimage-prod.moysklad.ru/static/tinyimage/7bf0a89f-c191-11ee-0a80-00d6000033ae/tinyimage/1438d84c-690c-4eea-be02-8f0c95dd6136/t.png",
            "imageURLMiniature": "https://miniature-prod.moysklad.ru/miniature/7bf0a89f-c191-11ee-0a80-00d6000033ae/documentminiature/3b542cc0-63fc-4d6b-aabe-5e93b63105ad",
            "imageURLOriginal": null,
            "price": 570.0,
            "vat": null,
            "currency": "руб",
            "uom": "шт",
            "quantity": 0.0,
            "stock": 0.0,
            "assortmentClass": "com.lognex.onlineorder.model.remap.OnlineOrderVariant",
            "isKit": false,
            "available": true
        },
        {
            "id": "f7fb62b4-3319-11f0-0a80-19c5002e05b9",
            "code": "05901",
            "article": null,
            "category": "ЭЛЕКТРОНКИ/SNOOPY SMOKE 40.000 ( 50 MG )",
            "categoryId": "6312fd42-3319-11f0-0a80-0f86002ea137",
            "name": "ЭЛ. СИГ. SNOOPY SMOKE 40.000 5% НИКОТИНА (ЛЕДЯНАЯ МЯТА)",
            "description": null,
            "imageURL": "https://tinyimage-prod.moysklad.ru/static/tinyimage/7bf0a89f-c191-11ee-0a80-00d6000033ae/tinyimage/1438d84c-690c-4eea-be02-8f0c95dd6136/t.png",
            "imageURLMiniature": "https://miniature-prod.moysklad.ru/miniature/7bf0a89f-c191-11ee-0a80-00d6000033ae/documentminiature/3b542cc0-63fc-4d6b-aabe-5e93b63105ad",
            "imageURLOriginal": null,
            "price": 570.0,
            "vat": null,
            "currency": "руб",
            "uom": "шт",
            "quantity": 0.0,
            "stock": 0.0,
            "assortmentClass": "com.lognex.onlineorder.model.remap.OnlineOrderVariant",
            "isKit": false,
            "available": true
        },
        {
            "id": "f7feccfe-3319-11f0-0a80-19c5002e05c3",
            "code": "05902",
            "article": null,
            "category": "ЭЛЕКТРОНКИ/SNOOPY SMOKE 40.000 ( 50 MG )",
            "categoryId": "6312fd42-3319-11f0-0a80-0f86002ea137",
            "name": "ЭЛ. СИГ. SNOOPY SMOKE 40.000 5% НИКОТИНА (МАРМЕЛАДНЫЕ МИШКИ)",
            "description": null,
            "imageURL": "https://tinyimage-prod.moysklad.ru/static/tinyimage/7bf0a89f-c191-11ee-0a80-00d6000033ae/tinyimage/1438d84c-690c-4eea-be02-8f0c95dd6136/t.png",
            "imageURLMiniature": "https://miniature-prod.moysklad.ru/miniature/7bf0a89f-c191-11ee-0a80-00d6000033ae/documentminiature/3b542cc0-63fc-4d6b-aabe-5e93b63105ad",
            "imageURLOriginal": null,
            "price": 570.0,
            "vat": null,
            "currency": "руб",
            "uom": "шт",
            "quantity": 0.0,
            "stock": 0.0,
            "assortmentClass": "com.lognex.onlineorder.model.remap.OnlineOrderVariant",
            "isKit": false,
            "available": true
        },
        {
            "id": "f80379f6-3319-11f0-0a80-19c5002e05cd",
            "code": "05903",
            "article": null,
            "category": "ЭЛЕКТРОНКИ/SNOOPY SMOKE 40.000 ( 50 MG )",
            "categoryId": "6312fd42-3319-11f0-0a80-0f86002ea137",
            "name": "ЭЛ. СИГ. SNOOPY SMOKE 40.000 5% НИКОТИНА (МЕКСИКАНСКОЕ МАНГО)",
            "description": null,
            "imageURL": "https://tinyimage-prod.moysklad.ru/static/tinyimage/7bf0a89f-c191-11ee-0a80-00d6000033ae/tinyimage/1438d84c-690c-4eea-be02-8f0c95dd6136/t.png",
            "imageURLMiniature": "https://miniature-prod.moysklad.ru/miniature/7bf0a89f-c191-11ee-0a80-00d6000033ae/documentminiature/3b542cc0-63fc-4d6b-aabe-5e93b63105ad",
            "imageURLOriginal": null,
            "price": 570.0,
            "vat": null,
            "currency": "руб",
            "uom": "шт",
            "quantity": 0.0,
            "stock": 0.0,
            "assortmentClass": "com.lognex.onlineorder.model.remap.OnlineOrderVariant",
            "isKit": false,
            "available": true
        },
        {
            "id": "f806ee1f-3319-11f0-0a80-19c5002e05d7",
            "code": "05904",
            "article": null,
            "category": "ЭЛЕКТРОНКИ/SNOOPY SMOKE 40.000 ( 50 MG )",
            "categoryId": "6312fd42-3319-11f0-0a80-0f86002ea137",
            "name": "ЭЛ. СИГ. SNOOPY SMOKE 40.000 5% НИКОТИНА (ПЕРСИК АРБУЗ ЛЕД)",
            "description": null,
            "imageURL": "https://tinyimage-prod.moysklad.ru/static/tinyimage/7bf0a89f-c191-11ee-0a80-00d6000033ae/tinyimage/1438d84c-690c-4eea-be02-8f0c95dd6136/t.png",
            "imageURLMiniature": "https://miniature-prod.moysklad.ru/miniature/7bf0a89f-c191-11ee-0a80-00d6000033ae/documentminiature/3b542cc0-63fc-4d6b-aabe-5e93b63105ad",
            "imageURLOriginal": null,
            "price": 570.0,
            "vat": null,
            "currency": "руб",
            "uom": "шт",
            "quantity": 0.0,
            "stock": 0.0,
            "assortmentClass": "com.lognex.onlineorder.model.remap.OnlineOrderVariant",
            "isKit": false,
            "available": true
        },
        {
            "id": "f80a5105-3319-11f0-0a80-19c5002e05e1",
            "code": "05905",
            "article": null,
            "category": "ЭЛЕКТРОНКИ/SNOOPY SMOKE 40.000 ( 50 MG )",
            "categoryId": "6312fd42-3319-11f0-0a80-0f86002ea137",
            "name": "ЭЛ. СИГ. SNOOPY SMOKE 40.000 5% НИКОТИНА (ПИНО КОЛАДА)",
            "description": null,
            "imageURL": "https://tinyimage-prod.moysklad.ru/static/tinyimage/7bf0a89f-c191-11ee-0a80-00d6000033ae/tinyimage/1438d84c-690c-4eea-be02-8f0c95dd6136/t.png",
            "imageURLMiniature": "https://miniature-prod.moysklad.ru/miniature/7bf0a89f-c191-11ee-0a80-00d6000033ae/documentminiature/3b542cc0-63fc-4d6b-aabe-5e93b63105ad",
            "imageURLOriginal": null,
            "price": 570.0,
            "vat": null,
            "currency": "руб",
            "uom": "шт",
            "quantity": 0.0,
            "stock": 0.0,
            "assortmentClass": "com.lognex.onlineorder.model.remap.OnlineOrderVariant",
            "isKit": false,
            "available": true
        },
        {
            "id": "f80df96d-3319-11f0-0a80-19c5002e05eb",
            "code": "05906",
            "article": null,
            "category": "ЭЛЕКТРОНКИ/SNOOPY SMOKE 40.000 ( 50 MG )",
            "categoryId": "6312fd42-3319-11f0-0a80-0f86002ea137",
            "name": "ЭЛ. СИГ. SNOOPY SMOKE 40.000 5% НИКОТИНА (РЕД БУЛЛ)",
            "description": null,
            "imageURL": "https://tinyimage-prod.moysklad.ru/static/tinyimage/7bf0a89f-c191-11ee-0a80-00d6000033ae/tinyimage/1438d84c-690c-4eea-be02-8f0c95dd6136/t.png",
            "imageURLMiniature": "https://miniature-prod.moysklad.ru/miniature/7bf0a89f-c191-11ee-0a80-00d6000033ae/documentminiature/3b542cc0-63fc-4d6b-aabe-5e93b63105ad",
            "imageURLOriginal": null,
            "price": 570.0,
            "vat": null,
            "currency": "руб",
            "uom": "шт",
            "quantity": 0.0,
            "stock": 0.0,
            "assortmentClass": "com.lognex.onlineorder.model.remap.OnlineOrderVariant",
            "isKit": false,
            "available": true
        },
        {
            "id": "f8121b77-3319-11f0-0a80-19c5002e05f5",
            "code": "05907",
            "article": null,
            "category": "ЭЛЕКТРОНКИ/SNOOPY SMOKE 40.000 ( 50 MG )",
            "categoryId": "6312fd42-3319-11f0-0a80-0f86002ea137",
            "name": "ЭЛ. СИГ. SNOOPY SMOKE 40.000 5% НИКОТИНА (РОЗОВЫЙ ЛИМОНАД)",
            "description": null,
            "imageURL": "https://tinyimage-prod.moysklad.ru/static/tinyimage/7bf0a89f-c191-11ee-0a80-00d6000033ae/tinyimage/1438d84c-690c-4eea-be02-8f0c95dd6136/t.png",
            "imageURLMiniature": "https://miniature-prod.moysklad.ru/miniature/7bf0a89f-c191-11ee-0a80-00d6000033ae/documentminiature/3b542cc0-63fc-4d6b-aabe-5e93b63105ad",
            "imageURLOriginal": null,
            "price": 570.0,
            "vat": null,
            "currency": "руб",
            "uom": "шт",
            "quantity": 0.0,
            "stock": 0.0,
            "assortmentClass": "com.lognex.onlineorder.model.remap.OnlineOrderVariant",
            "isKit": false,
            "available": true
        },
        {
            "id": "f8160f28-3319-11f0-0a80-19c5002e05ff",
            "code": "05908",
            "article": null,
            "category": "ЭЛЕКТРОНКИ/SNOOPY SMOKE 40.000 ( 50 MG )",
            "categoryId": "6312fd42-3319-11f0-0a80-0f86002ea137",
            "name": "ЭЛ. СИГ. SNOOPY SMOKE 40.000 5% НИКОТИНА (ТРОЙНЫЕ ЯГОДЫ ЛЕД)",
            "description": null,
            "imageURL": "https://tinyimage-prod.moysklad.ru/static/tinyimage/7bf0a89f-c191-11ee-0a80-00d6000033ae/tinyimage/1438d84c-690c-4eea-be02-8f0c95dd6136/t.png",
            "imageURLMiniature": "https://miniature-prod.moysklad.ru/miniature/7bf0a89f-c191-11ee-0a80-00d6000033ae/documentminiature/3b542cc0-63fc-4d6b-aabe-5e93b63105ad",
            "imageURLOriginal": null,
            "price": 570.0,
            "vat": null,
            "currency": "руб",
            "uom": "шт",
            "quantity": 0.0,
            "stock": 0.0,
            "assortmentClass": "com.lognex.onlineorder.model.remap.OnlineOrderVariant",
            "isKit": false,
            "available": true
        },
        {
            "id": "f8199d05-3319-11f0-0a80-19c5002e0609",
            "code": "05909",
            "article": null,
            "category": "ЭЛЕКТРОНКИ/SNOOPY SMOKE 40.000 ( 50 MG )",
            "categoryId": "6312fd42-3319-11f0-0a80-0f86002ea137",
            "name": "ЭЛ. СИГ. SNOOPY SMOKE 40.000 5% НИКОТИНА (ТРОПИЧЕСКИЙ  РАДУЖНЫЙ ВЗРЫВ)",
            "description": null,
            "imageURL": "https://tinyimage-prod.moysklad.ru/static/tinyimage/7bf0a89f-c191-11ee-0a80-00d6000033ae/tinyimage/1438d84c-690c-4eea-be02-8f0c95dd6136/t.png",
            "imageURLMiniature": "https://miniature-prod.moysklad.ru/miniature/7bf0a89f-c191-11ee-0a80-00d6000033ae/documentminiature/3b542cc0-63fc-4d6b-aabe-5e93b63105ad",
            "imageURLOriginal": null,
            "price": 570.0,
            "vat": null,
            "currency": "руб",
            "uom": "шт",
            "quantity": 0.0,
            "stock": 0.0,
            "assortmentClass": "com.lognex.onlineorder.model.remap.OnlineOrderVariant",
            "isKit": false,
            "available": true
        },
        {
            "id": "f81d21ac-3319-11f0-0a80-19c5002e0613",
            "code": "05910",
            "article": null,
            "category": "ЭЛЕКТРОНКИ/SNOOPY SMOKE 40.000 ( 50 MG )",
            "categoryId": "6312fd42-3319-11f0-0a80-0f86002ea137",
            "name": "ЭЛ. СИГ. SNOOPY SMOKE 40.000 5% НИКОТИНА (ЧЕРНИКА МАЛИНА)",
            "description": null,
            "imageURL": "https://tinyimage-prod.moysklad.ru/static/tinyimage/7bf0a89f-c191-11ee-0a80-00d6000033ae/tinyimage/1438d84c-690c-4eea-be02-8f0c95dd6136/t.png",
            "imageURLMiniature": "https://miniature-prod.moysklad.ru/miniature/7bf0a89f-c191-11ee-0a80-00d6000033ae/documentminiature/3b542cc0-63fc-4d6b-aabe-5e93b63105ad",
            "imageURLOriginal": null,
            "price": 570.0,
            "vat": null,
            "currency": "руб",
            "uom": "шт",
            "quantity": 0.0,
            "stock": 0.0,
            "assortmentClass": "com.lognex.onlineorder.model.remap.OnlineOrderVariant",
            "isKit": false,
            "available": true
        },
        {
            "id": "f821e9f1-3319-11f0-0a80-19c5002e061d",
            "code": "05911",
            "article": null,
            "category": "ЭЛЕКТРОНКИ/SNOOPY SMOKE 40.000 ( 50 MG )",
            "categoryId": "6312fd42-3319-11f0-0a80-0f86002ea137",
            "name": "ЭЛ. СИГ. SNOOPY SMOKE 40.000 5% НИКОТИНА (ЧЕРНИКА МАЛИНА ЛЕД)",
            "description": null,
            "imageURL": "https://tinyimage-prod.moysklad.ru/static/tinyimage/7bf0a89f-c191-11ee-0a80-00d6000033ae/tinyimage/1438d84c-690c-4eea-be02-8f0c95dd6136/t.png",
            "imageURLMiniature": "https://miniature-prod.moysklad.ru/miniature/7bf0a89f-c191-11ee-0a80-00d6000033ae/documentminiature/3b542cc0-63fc-4d6b-aabe-5e93b63105ad",
            "imageURLOriginal": null,
            "price": 570.0,
            "vat": null,
            "currency": "руб",
            "uom": "шт",
            "quantity": 0.0,
            "stock": 0.0,
            "assortmentClass": "com.lognex.onlineorder.model.remap.OnlineOrderVariant",
            "isKit": false,
            "available": true
        }
    ],
    "size": 21
}